odoo/addons/purchase_add_products_from_bom/README.rst
odoo/addons/purchase_add_products_from_bom/__init__.py
odoo/addons/purchase_add_products_from_bom/__manifest__.py
odoo/addons/purchase_add_products_from_bom/i18n/fr.po
odoo/addons/purchase_add_products_from_bom/i18n/pt_BR.po
odoo/addons/purchase_add_products_from_bom/i18n/purchase_add_products_from_bom.pot
odoo/addons/purchase_add_products_from_bom/models/__init__.py
odoo/addons/purchase_add_products_from_bom/models/product_product.py
odoo/addons/purchase_add_products_from_bom/readme/CONTRIBUTORS.rst
odoo/addons/purchase_add_products_from_bom/readme/DESCRIPTION.rst
odoo/addons/purchase_add_products_from_bom/readme/HISTORY.rst
odoo/addons/purchase_add_products_from_bom/readme/INSTALL.rst
odoo/addons/purchase_add_products_from_bom/readme/USAGE.rst
odoo/addons/purchase_add_products_from_bom/static/description/icon.png
odoo/addons/purchase_add_products_from_bom/static/description/index.html
odoo/addons/purchase_add_products_from_bom/tests/__init__.py
odoo/addons/purchase_add_products_from_bom/tests/test_purchase_add_products_from_bom.py
odoo/addons/purchase_add_products_from_bom/views/purchase_order_view.xml
odoo/addons/purchase_add_products_from_bom/wizard/__init__.py
odoo/addons/purchase_add_products_from_bom/wizard/add_products_from_bom.py
odoo/addons/purchase_add_products_from_bom/wizard/add_products_from_bom_view.xml
odoo12_addon_purchase_add_products_from_bom-12.0.1.0.0.99.dev4.dist-info/METADATA
odoo12_addon_purchase_add_products_from_bom-12.0.1.0.0.99.dev4.dist-info/WHEEL
odoo12_addon_purchase_add_products_from_bom-12.0.1.0.0.99.dev4.dist-info/top_level.txt
odoo12_addon_purchase_add_products_from_bom-12.0.1.0.0.99.dev4.dist-info/RECORD
